pyscomotif/RMSD_calculation.py
pyscomotif/__init__.py
pyscomotif/constants.py
pyscomotif/data_containers.py
pyscomotif/index_folders_and_files.py
pyscomotif/indexing.py
pyscomotif/motif_search.py
pyscomotif/motif_search_with_ShareableList.py
pyscomotif/pyscomotif.py
pyscomotif/residue_data_dicts.py
pyscomotif/utils.py
pyscomotif-0.9.50.dist-info/entry_points.txt
pyscomotif-0.9.50.dist-info/WHEEL
pyscomotif-0.9.50.dist-info/METADATA
pyscomotif-0.9.50.dist-info/RECORD
