Metadata-Version: 2.1
Name: pyscomotif
Version: 0.9.50
Summary: A python tool for the discovery of similar 3D structural motifs across proteins.
Author-email: Gabriel Cia <gabriel-_cia@hotmail.com>
Requires-Python: >=3.9
Requires-Dist: numba
Requires-Dist: click
Requires-Dist: biopython <= 1.79
Requires-Dist: networkx
Requires-Dist: scipy
Requires-Dist: pandas
Requires-Dist: numpy
Requires-Dist: typing_extensions
Requires-Dist: tqdm
Requires-Dist: joblib >= 1.3.2
Project-URL: Home, https://github.com/3BioCompBio/pyScoMotif
Project-URL: changelog, https://github.com/3BioCompBio/pyScoMotif/CHANGELOG.md
